azayaka/__init__.py
azayaka-0.1.0.dist-info/licenses/LICENSE
azayaka-0.1.0.dist-info/METADATA
azayaka-0.1.0.dist-info/WHEEL
azayaka-0.1.0.dist-info/top_level.txt
azayaka-0.1.0.dist-info/RECORD
