Metadata-Version: 2.4
Name: azayaka
Version: 0.1.0
Summary: SAR/InSAR processing utilities with geometry calculations for JAXA CEOS and SICD formats.
Author-email: yasui syusuke <syuchimu@gmail.com>, yamamoto yutaka <syuchimu@gmail.com>
License:                     GNU AFFERO GENERAL PUBLIC LICENSE
Keywords: SAR,InSAR,CEOS,SICD,remote-sensing,radar
Classifier: Development Status :: 3 - Alpha
Classifier: Intended Audience :: Science/Research
Classifier: License :: OSI Approved :: GNU Affero General Public License v3
Classifier: Programming Language :: Python :: 3
Classifier: Programming Language :: Python :: 3.11
Classifier: Programming Language :: Python :: 3.12
Classifier: Topic :: Scientific/Engineering :: GIS
Classifier: Topic :: Scientific/Engineering :: Image Processing
Requires-Python: >=3.11
License-File: LICENSE
Dynamic: license-file
